{
    "name": "Taiwan",
    "native": "\u81fa\u7063",
    "phone": "886",
    "continent": "AS",
    "capital": "Taipei",
    "currency": "TWD",
    "languages": "zh",
    "subdivisions": {
        "TW-KHH": "Kaohsiung",
        "TW-TPE": "Taipei",
        "TW-CYI": "Chiayi",
        "TW-HSZ": "Hsinchu",
        "TW-KEE": "Keelung",
        "TW-TXG": "Taichung",
        "TW-TNN": "Tainan",
        "TW-CHA": "Changhua",
        "TW-HUA": "Hualien",
        "TW-ILA": "Ilan",
        "TW-MIA": "Miaoli",
        "TW-NAN": "Nantou",
        "TW-PEN": "Penghu",
        "TW-PIF": "Pingtung",
        "TW-TTT": "Taitung",
        "TW-TAO": "Taoyuan",
        "TW-YUN": "Yunlin"
    }
}